dxchainpy
