Metadata-Version: 2.1
Name: dxchainpy
Version: 0.3.6.1
Summary: Toolkit that allows users to interact with dxchain
Home-page: https://github.com/DxChainNetwork/dxchainpy
Author: DxChain
Author-email: developer@dxchain.com
License: MIT
Platform: UNKNOWN
